<xml xmlns="https://developers.google.com/blockly/xml"><block type="component_event" id="f-1jgK/x)Y`=JC8zzxZ." x="371" y="19"><mutation xmlns="http://www.w3.org/1999/xhtml" component_name="camera" component_type="Button" parent_id="undefined" event_id="Click" was_updated="true"/><field name="component_id">4dd1877f-9488-42f7-b0ee-1072ac87f02b</field><field name="event_id">Click</field><statement name="input_do"><block type="setter" id="EaOGqQaG?MOLqYw,d]hM"><mutation xmlns="http://www.w3.org/1999/xhtml" component_name="PhotoViewer"/><field name="component_id">ef731430-34b6-44b9-bd32-c29a113c66bf</field><field name="field_name">Picture</field><value name="field_value"><shadow type="asset_get" id="2yG1}IDH~;a.T``tq5)b"><mutation xmlns="http://www.w3.org/1999/xhtml" previous_asset_name="305soft-high-resolution-logo-black-on-transparent-background.png" previous_asset_value="65b87a489b5b6433b9381a43"/><field name="ASSET">65b87a489b5b6433b9381a43</field></shadow><block type="camera_take_photo" id="~+gG^}W`ExT,unPLI.T`"/></value><next><block type="controls_if" id="WafT~hedS,yV8O_Y((5^"><value name="IF0"><block type="set_get" id="nGqT1P_k(~S-e{A6CAyl"><mutation xmlns="http://www.w3.org/1999/xhtml" component_name="confirmationSwitch"/><field name="component_id">ff5aa56a-a71b-4ca3-914d-071f3435fe0d</field><field name="field_name">value</field></block></value><statement name="DO0"><block type="speech_speak_text" id="YA86F(FzETxM%Zo#NMgs"><value name="TEXT"><shadow type="text" id="g+K.k#k4rWt:`_Jz$@,|"><field name="TEXT">Picture taken</field></shadow></value><value name="LANGUAGE"><shadow type="device_language" id="yPmr$*IfW:ilOukA/=JQ"><mutation xmlns="http://www.w3.org/1999/xhtml" parent_block_name="speech_speak_text"/><field name="LANGUAGE">en-US</field></shadow></value></block></statement></block></next></block></statement></block><block type="component_event" id="$Jl,)~x%/FcoH/8-R!iv" x="350" y="201"><mutation xmlns="http://www.w3.org/1999/xhtml" component_name="PhotoLibrary" component_type="Button" parent_id="undefined" event_id="Click" was_updated="true"/><field name="component_id">bcf8b149-894a-485f-aa2c-a5cc8349cb2c</field><field name="event_id">Click</field><statement name="input_do"><block type="setter" id="a7x%+stza2}87m2w)tg)"><mutation xmlns="http://www.w3.org/1999/xhtml" component_name="PhotoViewer"/><field name="component_id">ef731430-34b6-44b9-bd32-c29a113c66bf</field><field name="field_name">Picture</field><value name="field_value"><shadow type="asset_get" id="2yG1}IDH~;a.T``tq5)b"><mutation xmlns="http://www.w3.org/1999/xhtml" previous_asset_name="305soft-high-resolution-logo-black-on-transparent-background.png" previous_asset_value="65b87a489b5b6433b9381a43"/><field name="ASSET">65b87a489b5b6433b9381a43</field></shadow><block type="camera_select_photo" id="-V{]rPQ@X4]_VOH!0|wx"><field name="MEDIA_TYPE_OPTIONS">PHOTO</field></block></value></block></statement></block><block type="component_event" id="RtXIPEHpV;5n9R]/L.Ei" x="345" y="295"><mutation xmlns="http://www.w3.org/1999/xhtml" component_name="Describe" component_type="Button" parent_id="undefined" event_id="Click" was_updated="true"/><field name="component_id">baec0fb4-6d42-43fd-bfcb-d607335bf347</field><field name="event_id">Click</field><statement name="input_do"><block type="setter" id="x{qD@]m=DgV~=gqdoxN["><mutation xmlns="http://www.w3.org/1999/xhtml" component_name="DescriptionLabel"/><field name="component_id">97787a89-9a3d-4d1d-a10b-11d5b3240d42</field><field name="field_name">Text</field><value name="field_value"><shadow type="text" id="l!:L4*hPF2.F/a}vY/NS"><field name="TEXT">Label</field></shadow><block type="camera_describe_image" id="yj/K1(CO)+B!PTXQS05h"><value name="IMAGE"><shadow type="camera_take_photo" id="ZxdUX0h)~C7mA~8BubEj"/><block type="set_get" id="nELZcck]}k0#_WQnusd*"><mutation xmlns="http://www.w3.org/1999/xhtml" component_name="PhotoViewer"/><field name="component_id">ef731430-34b6-44b9-bd32-c29a113c66bf</field><field name="field_name">Picture</field></block></value></block></value></block></statement></block><block type="component_event" id="%68hVy3,YTg~bu=LHY/~" x="353" y="402"><mutation xmlns="http://www.w3.org/1999/xhtml" component_name="Scan" component_type="Button" parent_id="undefined" event_id="Click" was_updated="true"/><field name="component_id">8ff9f43b-48e2-4e7d-adae-554714858558</field><field name="event_id">Click</field><statement name="input_do"><block type="setter" id="wvBN*L5gdc$)K`_Wvp5?"><mutation xmlns="http://www.w3.org/1999/xhtml" component_name="DescriptionLabel"/><field name="component_id">97787a89-9a3d-4d1d-a10b-11d5b3240d42</field><field name="field_name">Text</field><value name="field_value"><shadow type="text" id="y]E-tn8whhXCN0M3=ld7"><field name="TEXT">Label</field></shadow><block type="camera_scan_barcode" id="_[$MdOB9F0/@jz}Y@t{P"><field name="CAMERA_OPTIONS">back</field></block></value></block></statement></block><block type="component_event" id="FqOf7Dm[~$|{-+`rO$k$" x="367" y="517"><mutation xmlns="http://www.w3.org/1999/xhtml" component_name="Upload" component_type="Button" parent_id="undefined" event_id="Click" was_updated="true"/><field name="component_id">26a079df-7bbe-4a5d-a5be-0fe5dd3e3600</field><field name="event_id">Click</field><statement name="input_do"><block type="setter" id="6iBlcIQINaGg1K:XU3@J"><mutation xmlns="http://www.w3.org/1999/xhtml" component_name="DescriptionLabel"/><field name="component_id">97787a89-9a3d-4d1d-a10b-11d5b3240d42</field><field name="field_name">Text</field><value name="field_value"><shadow type="text" id="}%}%q$;2G@eJ^Qaikc%c"><field name="TEXT">Label</field></shadow><block type="camera_upload_image" id="6ERbQ4vwP/bmK-Uk~bOm"><value name="IMAGE"><shadow type="asset_get" id="%!#JFHz5Npp69/_#ybRP"><mutation xmlns="http://www.w3.org/1999/xhtml" previous_asset_name="305soft-high-resolution-logo-black-on-transparent-background.png" previous_asset_value="65b87a489b5b6433b9381a43"/><field name="ASSET">65b87a489b5b6433b9381a43</field></shadow><block type="set_get" id="cxlrH6rKiuX)96Q-VBT9"><mutation xmlns="http://www.w3.org/1999/xhtml" component_name="PhotoViewer"/><field name="component_id">ef731430-34b6-44b9-bd32-c29a113c66bf</field><field name="field_name">Picture</field></block></value></block></value></block></statement></block><block type="component_event" id="S=Ty^;jO^JW8oQn::^{f" x="371" y="692"><mutation xmlns="http://www.w3.org/1999/xhtml" component_name="barcode" component_type="Button" parent_id="undefined" event_id="Click" was_updated="true"/><field name="component_id">fa9d36c7-e3b0-4148-9819-433ac0347304</field><field name="event_id">Click</field><statement name="input_do"><block type="setter" id="OhWuC,wXaYE~FG}IEC[("><mutation xmlns="http://www.w3.org/1999/xhtml" component_name="DescriptionLabel"/><field name="component_id">97787a89-9a3d-4d1d-a10b-11d5b3240d42</field><field name="field_name">Text</field><value name="field_value"><shadow type="text" id="}%}%q$;2G@eJ^Qaikc%c"><field name="TEXT">Label</field></shadow><block type="camera_scan_barcode" id="GhC7tOEH{lD6zLsrv;lE"><field name="CAMERA_OPTIONS">back</field></block></value></block></statement></block></xml>